Workbook

Sheet GC
H3: * "interest" or exact number | K3: * "bullet" or exact number
G5: Interest | J5: Principal
G6: Repayment Date | H6: Amount* | J6: Repayment Date | K6: Amount*
C9: Loan Provided
C10: Funding Date
C11: Maturity Date
C12: Interest Rate
C13: Interest Repayment | D13: lump-sum
F21: =ROUND(F22,2)=ROUND(SUM(G22:G22),2) -> TRUE
B22: ∑ | C22: Cash flow | F22: =SUM(F25:F144) -> 0 | G22: =SUM(G25:G144) -> 0 | I22: =SUM(I25:I144) -> 0 | K22: =SUM(K25:K144) -> 0
B23: # | C23: Month (calendar) | D23: Repayment Interest | E23: Repayment PV | F23: Interest Due (net) | G23: Interest Paid | H23: Interest Left | I23: Principal Paid | J23: Principal Left | K23: GC
B24: 0 | C24: =D10 -> 0 | H24: =F24-G24 -> 0 | J24: =D9 -> 0
B25: 1 | C25: =EOMONTH(C24,1) -> 59 | D25: =IF(E25="bullet","interest",IFERROR(INDEX($H$7:$H$18,MATCH(C25,$G$7:$G$18,0)),"n/a")) -> n/a | E25: =IF(C25=$D$11,"bullet",IFERROR(INDEX($K$7:$K$18,MATCH(C25,$J$7:$J$18,0)),"n/a")) -> n/a | F25: =J24*$D$12*(C25-C24+1)/360 -> 0 | G25: =IF(D25="n/a",0,MIN(D25,F25+H24)) -> 0 | H25: =H24+F25-G25 -> 0 | I25: =IF(E25="n/a",0,IF(E25="bullet",J24,MIN(E25,J24))) -> 0 | J25: =J24-I25 -> 0 | K25: =G25+I25 -> 0
B26: 2 | C26: =EOMONTH(C25,1) -> 91 | D26: =IF(E26="bullet","interest",IFERROR(INDEX($H$7:$H$18,MATCH(C26,$G$7:$G$18,0)),"n/a")) -> n/a | E26: =IF(C26=$D$11,"bullet",IFERROR(INDEX($K$7:$K$18,MATCH(C26,$J$7:$J$18,0)),"n/a")) -> n/a | F26: =J25*$D$12*(C26-C25)/360 -> 0 | G26: =IF(D26="n/a",0,MIN(D26,F26+H25)) -> 0 | H26: =H25+F26-G26 -> 0 | I26: =IF(E26="n/a",0,IF(E26="bullet",J25,MIN(E26,J25))) -> 0 | J26: =J25-I26 -> 0 | K26: =G26+I26 -> 0
B27: 3 | C27: =EOMONTH(C26,1) -> 121 | D27: =IF(E27="bullet","interest",IFERROR(INDEX($H$7:$H$18,MATCH(C27,$G$7:$G$18,0)),"n/a")) -> n/a | E27: =IF(C27=$D$11,"bullet",IFERROR(INDEX($K$7:$K$18,MATCH(C27,$J$7:$J$18,0)),"n/a")) -> n/a | F27: =J26*$D$12*(C27-C26)/360 -> 0 | G27: =IF(D27="n/a",0,MIN(D27,F27+H26)) -> 0 | H27: =H26+F27-G27 -> 0 | I27: =IF(E27="n/a",0,IF(E27="bullet",J26,MIN(E27,J26))) -> 0 | J27: =J26-I27 -> 0 | K27: =G27+I27 -> 0
B28: 4 | C28: =EOMONTH(C27,1) -> 152 | D28: =IF(E28="bullet","interest",IFERROR(INDEX($H$7:$H$18,MATCH(C28,$G$7:$G$18,0)),"n/a")) -> n/a | E28: =IF(C28=$D$11,"bullet",IFERROR(INDEX($K$7:$K$18,MATCH(C28,$J$7:$J$18,0)),"n/a")) -> n/a | F28: =J27*$D$12*(C28-C27)/360 -> 0 | G28: =IF(D28="n/a",0,MIN(D28,F28+H27)) -> 0 | H28: =H27+F28-G28 -> 0 | I28: =IF(E28="n/a",0,IF(E28="bullet",J27,MIN(E28,J27))) -> 0 | J28: =J27-I28 -> 0 | K28: =G28+I28 -> 0
B29: 5 | C29: =EOMONTH(C28,1) -> 182 | D29: =IF(E29="bullet","interest",IFERROR(INDEX($H$7:$H$18,MATCH(C29,$G$7:$G$18,0)),"n/a")) -> n/a | E29: =IF(C29=$D$11,"bullet",IFERROR(INDEX($K$7:$K$18,MATCH(C29,$J$7:$J$18,0)),"n/a")) -> n/a | F29: =J28*$D$12*(C29-C28)/360 -> 0 | G29: =IF(D29="n/a",0,MIN(D29,F29+H28)) -> 0 | H29: =H28+F29-G29 -> 0 | I29: =IF(E29="n/a",0,IF(E29="bullet",J28,MIN(E29,J28))) -> 0 | J29: =J28-I29 -> 0 | K29: =G29+I29 -> 0
B30: 6 | C30: =EOMONTH(C29,1) -> 213 | D30: =IF(E30="bullet","interest",IFERROR(INDEX($H$7:$H$18,MATCH(C30,$G$7:$G$18,0)),"n/a")) -> n/a | E30: =IF(C30=$D$11,"bullet",IFERROR(INDEX($K$7:$K$18,MATCH(C30,$J$7:$J$18,0)),"n/a")) -> n/a | F30: =J29*$D$12*(C30-C29)/360 -> 0 | G30: =IF(D30="n/a",0,MIN(D30,F30+H29)) -> 0 | H30: =H29+F30-G30 -> 0 | I30: =IF(E30="n/a",0,IF(E30="bullet",J29,MIN(E30,J29))) -> 0 | J30: =J29-I30 -> 0 | K30: =G30+I30 -> 0
B31: 7 | C31: =EOMONTH(C30,1) -> 244 | D31: =IF(E31="bullet","interest",IFERROR(INDEX($H$7:$H$18,MATCH(C31,$G$7:$G$18,0)),"n/a")) -> n/a | E31: =IF(C31=$D$11,"bullet",IFERROR(INDEX($K$7:$K$18,MATCH(C31,$J$7:$J$18,0)),"n/a")) -> n/a | F31: =J30*$D$12*(C31-C30)/360 -> 0 | G31: =IF(D31="n/a",0,MIN(D31,F31+H30)) -> 0 | H31: =H30+F31-G31 -> 0 | I31: =IF(E31="n/a",0,IF(E31="bullet",J30,MIN(E31,J30))) -> 0 | J31: =J30-I31 -> 0 | K31: =G31+I31 -> 0
B32: 8 | C32: =EOMONTH(C31,1) -> 274 | D32: =IF(E32="bullet","interest",IFERROR(INDEX($H$7:$H$18,MATCH(C32,$G$7:$G$18,0)),"n/a")) -> n/a | E32: =IF(C32=$D$11,"bullet",IFERROR(INDEX($K$7:$K$18,MATCH(C32,$J$7:$J$18,0)),"n/a")) -> n/a | F32: =J31*$D$12*(C32-C31)/360 -> 0 | G32: =IF(D32="n/a",0,MIN(D32,F32+H31)) -> 0 | H32: =H31+F32-G32 -> 0 | I32: =IF(E32="n/a",0,IF(E32="bullet",J31,MIN(E32,J31))) -> 0 | J32: =J31-I32 -> 0 | K32: =G32+I32 -> 0
B33: 9 | C33: =EOMONTH(C32,1) -> 305 | D33: =IF(E33="bullet","interest",IFERROR(INDEX($H$7:$H$18,MATCH(C33,$G$7:$G$18,0)),"n/a")) -> n/a | E33: =IF(C33=$D$11,"bullet",IFERROR(INDEX($K$7:$K$18,MATCH(C33,$J$7:$J$18,0)),"n/a")) -> n/a | F33: =J32*$D$12*(C33-C32)/360 -> 0 | G33: =IF(D33="n/a",0,MIN(D33,F33+H32)) -> 0 | H33: =H32+F33-G33 -> 0 | I33: =IF(E33="n/a",0,IF(E33="bullet",J32,MIN(E33,J32))) -> 0 | J33: =J32-I33 -> 0 | K33: =G33+I33 -> 0
B34: 10 | C34: =EOMONTH(C33,1) -> 335 | D34: =IF(E34="bullet","interest",IFERROR(INDEX($H$7:$H$18,MATCH(C34,$G$7:$G$18,0)),"n/a")) -> n/a | E34: =IF(C34=$D$11,"bullet",IFERROR(INDEX($K$7:$K$18,MATCH(C34,$J$7:$J$18,0)),"n/a")) -> n/a | F34: =J33*$D$12*(C34-C33)/360 -> 0 | G34: =IF(D34="n/a",0,MIN(D34,F34+H33)) -> 0 | H34: =H33+F34-G34 -> 0 | I34: =IF(E34="n/a",0,IF(E34="bullet",J33,MIN(E34,J33))) -> 0 | J34: =J33-I34 -> 0 | K34: =G34+I34 -> 0
B35: 11 | C35: =EOMONTH(C34,1) -> 366 | D35: =IF(E35="bullet","interest",IFERROR(INDEX($H$7:$H$18,MATCH(C35,$G$7:$G$18,0)),"n/a")) -> n/a | E35: =IF(C35=$D$11,"bullet",IFERROR(INDEX($K$7:$K$18,MATCH(C35,$J$7:$J$18,0)),"n/a")) -> n/a | F35: =J34*$D$12*(C35-C34)/360 -> 0 | G35: =IF(D35="n/a",0,MIN(D35,F35+H34)) -> 0 | H35: =H34+F35-G35 -> 0 | I35: =IF(E35="n/a",0,IF(E35="bullet",J34,MIN(E35,J34))) -> 0 | J35: =J34-I35 -> 0 | K35: =G35+I35 -> 0
B36: 12 | C36: =EOMONTH(C35,1) -> 397 | D36: =IF(E36="bullet","interest",IFERROR(INDEX($H$7:$H$18,MATCH(C36,$G$7:$G$18,0)),"n/a")) -> n/a | E36: =IF(C36=$D$11,"bullet",IFERROR(INDEX($K$7:$K$18,MATCH(C36,$J$7:$J$18,0)),"n/a")) -> n/a | F36: =J35*$D$12*(C36-C35)/360 -> 0 | G36: =IF(D36="n/a",0,MIN(D36,F36+H35)) -> 0 | H36: =H35+F36-G36 -> 0 | I36: =IF(E36="n/a",0,IF(E36="bullet",J35,MIN(E36,J35))) -> 0 | J36: =J35-I36 -> 0 | K36: =G36+I36 -> 0
B37: 13 | C37: =EOMONTH(C36,1) -> 425 | D37: =IF(E37="bullet","interest",IFERROR(INDEX($H$7:$H$18,MATCH(C37,$G$7:$G$18,0)),"n/a")) -> n/a | E37: =IF(C37=$D$11,"bullet",IFERROR(INDEX($K$7:$K$18,MATCH(C37,$J$7:$J$18,0)),"n/a")) -> n/a | F37: =J36*$D$12*(C37-C36)/360 -> 0 | G37: =IF(D37="n/a",0,MIN(D37,F37+H36)) -> 0 | H37: =H36+F37-G37 -> 0 | I37: =IF(E37="n/a",0,IF(E37="bullet",J36,MIN(E37,J36))) -> 0 | J37: =J36-I37 -> 0 | K37: =G37+I37 -> 0
... B144: 120 | C144: =EOMONTH(C143,1) -> 3684 | D144: =IF(E144="bullet","interest",IFERROR(INDEX($H$7:$H$18,MATCH(C144,$G$7:$G$18,0)),"n/a")) -> n/a | E144: =IF(C144=$D$11,"bullet",IFERROR(INDEX($K$7:$K$18,MATCH(C144,$J$7:$J$18,0)),"n/a")) -> n/a | F144: =J143*$D$12*(C144-C143)/360 -> 0 | G144: =IF(D144="n/a",0,MIN(D144,F144+H143)) -> 0 | H144: =H143+F144-G144 -> 0 | I144: =IF(E144="n/a",0,IF(E144="bullet",J143,MIN(E144,J143))) -> 0 | J144: =J143-I144 -> 0 | K144: =G144+I144 -> 0

Sheet Summary&CF_SICAV
M3: Gross | P3: Net | X3: Values | Y3: Ends | Z3: Blank | AA3: Up | AB3: Down
D4: all data in EUR | U4: MV | V4: =E20/1000000 -> 0 | X4: =V4 -> 0 | Y4: =X4 -> 0
M5: TOTAL | P5: TOTAL | U5: GC Total (after WHT on Interesat) | V5: =E94/1000000 -> 0 | W5: =V5-V4 -> 0 | X5: =W5 -> 0 | Z5: =MIN(SUM(X$4:X4),SUM(X$4:X5)) -> 0 | AA5: =MAX(X5,0) -> 0 | AB5: =-MIN(X5,0) -> 0
D6: Transaction description | E6: Total | U6: MSF + VAT + Local Fees | V6: =SUM(R126:R245)/1000000 -> #DIV/0! | W6: =V6-V5 -> #DIV/0! | X6: =W6 -> #DIV/0! | Z6: =MIN(SUM(X$4:X5),SUM(X$4:X6)) -> #DIV/0! | AA6: =MAX(X6,0) -> #DIV/0! | AB6: =-MIN(X6,0) -> #DIV/0!
D7: Seller | M7: Daily IRR model hard copy | N7: =(1+XIRR(AZ125:AZ245,D125:D245))^(1/365)-1 -> #NUM! | P7: Daily IRR model hard copy | Q7: =(1+XIRR(AL125:AL245,D125:D245))^(1/365)-1 -> #NUM! | U7: Taxes + 2nd Layer + SICAV | V7: =SUM(AO126:AO245)/1000000 -> #NUM! | W7: =V7-V6 -> #NUM! | X7: =W7 -> #NUM! | Z7: =MIN(SUM(X$4:X6),SUM(X$4:X7)) -> #DIV/0! | AA7: =MAX(X7,0) -> #NUM! | AB7: =-MIN(X7,0) -> #NUM!
D8: Country | M8: Principal EoP | N8: =BD245 -> #NUM! | P8: Principal EoP | Q8: =BH245 -> #NUM! | U8: Carry | V8: =SUM(AV126:AV245)/1000000 -> #NUM! | W8: =V8-V7 -> #NUM! | X8: =W8 -> #NUM! | Z8: =MIN(SUM(X$4:X7),SUM(X$4:X8)) -> #DIV/0! | AA8: =MAX(X8,0) -> #NUM! | AB8: =-MIN(X8,0) -> #NUM!
D9: Type of the portfolio | M9: Check 1 | N9: =ROUND(BB123+BC123,0)=ROUND(H123,0) -> #NUM! | P9: Check 1 | Q9: =ROUND(BF123+BG123,0)=ROUND(AL123-AL125,0) -> #NUM! | U9: Net collections after tax and carry | Y9: =SUM(X4:X8) -> #DIV/0!
D10: Type of the bid price submission | M10: Check 2 | N10: =N8<1000 -> #NUM! | P10: Check 2 | Q10: =Q8<1000 -> #NUM!
D11: Binding bid | M11: Check 3 | N11: =ROUND((AC123+V123)/(R123+Q123),3)=1 -> #NUM!
D12: Cut off date
D14: Portfolio overview | E14: Total
D15: Nominal value | E15: =GC!D9 -> 0
D16: Principal value | E16: =E15 -> 0
D17: Number of loans | E17: 1
D18: Number of clients | E18: 1
D19: Number of unique collaterals with BMV>0 | E19: 0
D20: Bank`s market value of NPL Collateral | E20: 0
D21: Average size of the loan | E21: =E15/E17 -> 0
D23: Main assumptions | F23: Comments
D24: WHT on Loan Interest | F24: of gross interest paid
C25: Local SPV | D25: Agent Fee | F25: of gross collections
D26: Success fee Threshold 1 | E26: 0 | F26: of net multiple before tax
D27: Success fee after Threshold 1 | E27: 0 | F27: of gross collections
D28: Success fee Threshold 2 | E28: 0 | F28: of net multiple before tax
D29: Success fee after Threshold 2 | E29: 0 | F29: of gross collections
D30: VAT on Agent Fee | E30: 0 | F30: applied on Agent Fee
D31: VAT applied on X% of Agent Fee | E31: 0
D32: Monthly SPV OPEX Local | E32: 0 | F32: EUR
D33: Facility Agent Fee | E33: 0 | F33: EUR
D34: SPV OPEX and FAF paid until month X | E34: 0 | F34: month
D35: VAT on FAF | E35: 0 | F35: applied on FMF
D36: Risk Premium Local | E36: 0 | F36: incl. CIT
D37: Annual Interest Rate | E37: 0.05 | F37: for the loan provided by Delta
D38: Daily Interest Rate | E38: =(1+E37)^(1/365)-1 -> 0.00013368062 | F38: calculated from Annual Int. R.
D39: WHT Fixed Interest | E39: 0
D40: WHT Variable Interest | E40: 0
D41: Income tax (CIT) | E41: 0
D42: Entity Liquidation Costs | E42: 0 | F42: EUR
C43: 2nd Layer | D43: MIP Expenses | E43: 0 | F43: of NCF
D44: Tax on Risk Premium | E44: 0 | F44: (cost of servicer)
D45: SPV OPEX 2nd Layer | E45: 0 | F45: EUR
D46: FMF 2nd Layer | E46: 0 | F46: EUR
D47: SPV OPEX and FMF 2nd Layer paid until month X | E47: 0 | F47: month
C48: SICAV | D48: SICAV Costs | F48: of NPV (monthly rate)
D49: Additional costs SICAV | E49: 0 | F49: EUR
D50: Additional costs paid until month X | E50: 0 | F50: month
C51: Carry | D51: Carry after Threshold 1 | E51: 0 | F51: of collections
D52: Carry Threshold 1 | E52: 0 | F52: IRR
D53: Carry Catch-up 1 | E53: Yes
D54: Carry after Threshold 2 | E54: 0 | F54: of collections
D55: Carry Threshold 2 | E55: 0 | F55: IRR
D56: Carry Catch-up 2 | E56: No
C57: One - Off | D57: Engagement Fee (DD+Closing) | E57: 0 | F57: EUR
D58: Underwriting Fee | E58: 0 | F58: % of PP
D59: Borrower's Costs | E59: 0 | F59: EUR
D60: Closing costs as % out of PP | E60: 0 | F60: of Purchase price
D61: MSF prepaid | E61: 0 | F61: EUR
D62: Notification letters | E62: 0 | F62: EUR per loan
D63: Notarization costs | E63: 0 | F63: EUR
D64: VAT applied on One - Off Costs | E64: 0
D65: MIP Subscription Costs | E65: 0
D67: Investment overview | E67: Total | F67: Comments
D68: Purchase Price (% out of Nominal value) | E68: =E72/E15 -> #DIV/0!
D69: Purchase Price (% out of Principal value) | E69: =E72/E16 -> #DIV/0!
D70: Purchase Price (% out of Bank market value) | E70: =IFERROR(E72/E20, "n/a") -> n/a
D71: Price/UPB Net of PCC | E71: =E77/E16 -> #DIV/0!
D72: Purchase price | E72: =GC!D9 -> 0
C73: PCC | D73: VDR Voluntary payments | E73: 0
D74: VDR Sale of collaterals | E74: 0
D75: Assumed Voluntary payments | E75: 0
D76: Assumed Sale of collaterals | E76: 0
D77: Purchase price minus PCC | E77: =E72-SUM(E73:E76) -> 0
C78: One - Off Costs | D78: Engagement Fee (DD+Closing) | E78: =E57 -> 0
D79: Underwriting Fee | E79: =E58*E72 -> 0
D80: Borrower's Costs | E80: =E59 -> 0
D81: Closing costs as % out of PP | E81: =E60*E72 -> 0
D82: MSF prepaid | E82: =E61 -> 0 | F82: =I123-J123=E82 -> TRUE
D83: Notification letters | E83: =E62*E17 -> 0
D84: Notarization costs | E84: =E63 -> 0
D85: VAT | E85: =SUM(E78:E79,E81:E84)*$E$64 -> 0
D86: MIP Subscription Costs | E86: =E65*SUM(E77:E85) -> 0 | H86: Engagement Fee
D87: Total Investment | E87: =SUM(E77:E86) -> 0 | F87: =ROUND(E94-SUM(E98:E115)-E87,5)=ROUND(E92,5) -> #DIV/0! | H87: Arrangement Fee
D88: Total Investment (% of nominal value) | E88: =IFERROR(E87/E15,0) -> 0
C89: Model Outcome | D89: ="XIRR (after tax"&IF($E$115<>0," and carry)",")") -> XIRR (after tax) | E89: =AW123 -> -1 | H89: APS Fees | I89: Total
D90: ="Net Break Event Point (after tax"&IF($E$115<>0," and carry)",")") -> Net Break Event Point (after tax) | E90: =IFERROR(MATCH(1,AX126:AX245,0),"-") -> - | F90: months | H90: Current Year | I90: 2025
D91: ="Net Multiple (after tax"&IF($E$115<>0," and carry)",")") -> Net Multiple (after tax) | E91: =E92/E87+1 -> #NUM! | H91: APS fees total | I91: =I92+I95 -> 0
D92: ="Net Profit (after tax"&IF($E$115<>0," and carry)",")") -> Net Profit (after tax) | E92: =AV123 -> #NUM! | F92: =ROUND(E93-E92,0)=ROUND(E87,0) -> #DIV/0! | H92: New AMF total | I92: 0
D93: ="Net Collections (after tax"&IF($E$115<>0," and carry)",")") -> Net Collections (after tax) | E93: =E94-SUM(E98:E115) -> #DIV/0! | F93: =ROUND(E93,2)=ROUND(SUM(AV126:AV245),2) -> #DIV/0! | H93: ="New AMF "&I90 -> New AMF 2025 | I93: 0
D94: GC Total | E94: =SUM(E116:E118) -> 0 | F94: =TEXT(E94/$E$20-1,"0,0%")&" Cut to BMV" -> #DIV/0! | H94: ="APSI fees "&I90 -> APSI fees 2025 | I94: =I86+I87 -> 0
D95: Gross Multiple | E95: =E94/E87 -> #DIV/0! | H95: APSI fees total | I95: =I86+I87 -> 0
D96: Weighted Average Life | E96: =SUMPRODUCT(H126:H245,C126:C245)/H123 -> #DIV/0! | F96: months
D97: Recovery Rate | E97: =IFERROR(E94/E15,0) -> 0
D98: Agent Fee | E98: =J123 -> 0 | F98: =ROUND((E98+E82)/E94,5)=E25 -> #DIV/0!
D99: Success fee 1 | E99: =K123 -> #DIV/0! | F99: =IF(E99=0,"TRUE",ROUND(E99/SUMIF(BI126:BI245,"<>"&0,H126:H245),5)=ROUND(E27,5)) -> #DIV/0!
D100: Success fee 2 | E100: =L123 -> #DIV/0! | F100: =IF(E100=0,"TRUE",ROUND(E100/SUMIF(BI126:BI245,2,H126:H245),5)=ROUND(E29,5)) -> #DIV/0!
D101: VAT on Agent Fee | E101: =M123 -> #DIV/0! | F101: =ROUND(E101/(E98+E99+E100),5)=ROUND(E30*E31,5) -> #DIV/0!
D102: SPV OPEX Local | E102: =N123 -> 0
D103: Facility Agent Fee | E103: =O123 -> 0
D104: VAT on FAF | E104: =P123 -> 0 | F104: =IF(E103=0,"TRUE",ROUND(E104/E103,5)=ROUND(E35,5)) -> TRUE
D105: Risk Premium Local | E105: =Q123 -> 0
...
